yada/__init__.py
yada/cli/__init__.py
yada/cli/main.py
yada/config.py
yada/data/__init__.py
yada/data/config.yaml
yada/exceptions.py
yada/platform.py
yada/repo.py
yada/xdg.py
yada-0.9.11.dist-info/METADATA
yada-0.9.11.dist-info/WHEEL
yada-0.9.11.dist-info/entry_points.txt
yada-0.9.11.dist-info/RECORD
