Metadata-Version: 2.1
Name: yada
Version: 0.9.11
Summary: Yet another dotfile aggregator
License: MIT
Author: Adrian Petrescu
Author-email: adrian@apetre.sc
Requires-Python: >=3.9,<4.0
Classifier: License :: OSI Approved :: MIT License
Classifier: Programming Language :: Python :: 3
Classifier: Programming Language :: Python :: 3.9
Classifier: Programming Language :: Python :: 3.10
Classifier: Programming Language :: Python :: 3.11
Classifier: Programming Language :: Python :: 3.12
Requires-Dist: click (>=7.0,<8.0)
Requires-Dist: pyyaml (!=5.4.0,!=5.4.1,!=6.0.0)
